Workbook

Sheet DashBoard
A1: DashBoard
T6: Product | U6: Sum of Revenue
T7: Keyboard | U7: 11650
T8: Laptop | U8: 60300
T9: Monitor | U9: 28500
T10: Mouse | U10: 9375
T11: Smartphone | U11: 92400
T12: Tablet | U12: 33600
T13: Grand Total | U13: 235825

Sheet  Monthly Revenue
A3: Month | B3: Sum of Revenue
A4: 1 | B4: 116500
A5: 2 | B5: 119325
A6: Grand Total | B6: 235825

Sheet Region Wise Revenue
A3: Region | B3: Sum of Revenue
A4: East | B4: 76150
A5: North | B5: 88200
A6: South | B6: 35275
A7: West | B7: 36200
A8: Grand Total | B8: 235825

Sheet Qty Sold of Products
A3: Product | B3: Sum of Units_Sold
A4: Keyboard | B4: 233
A5: Laptop | B5: 67
A6: Monitor | B6: 114
A7: Mouse | B7: 375
A8: Smartphone | B8: 132
A9: Tablet | B9: 84
A10: Grand Total | B10: 1005

Sheet Product Wise Revenue
A3: Product | B3: Sum of Revenue
A4: Keyboard | B4: 11650
A5: Laptop | B5: 60300
A6: Monitor | B6: 28500
A7: Mouse | B7: 9375
A8: Smartphone | B8: 92400
A9: Tablet | B9: 33600
A10: Grand Total | B10: 235825

Sheet Revenue Through Sales Channel
A3: Sales_Channel | B3: Sum of Revenue
A4: Online | B4: 81675
A5: Retail | B5: 88825
A6: Wholesale | B6: 65325
A7: Grand Total | B7: 235825

Sheet Project Database
A1: Date | B1: Region | C1: Product | D1: Units_Sold | E1: Unit_Price | F1: Dicount | G1: Revenue | H1: Sales_Person | I1: Sales_Channel | J1: Month | K1: Filtering
A2: 45292 | B2: North | C2: Laptop | D2: 5 | E2: 900 | F2: =IF(C2="Laptop",10%, IF(C2="Tablet",8%, IF(C2="Smartphone",12%, IF(C2="Monitor",7%, IF(C2="Keyboard",5%, IF(C2="Mouse",5%,0)))))) -> 0.1 | G2: 4500 | H2: Alex | I2: Online | J2: =MONTH(A2) -> 1
A3: 45293 | B3: South | C3: Tablet | D3: 8 | E3: 400 | F3: =IF(C3="Laptop",10%, IF(C3="Tablet",8%, IF(C3="Smartphone",12%, IF(C3="Monitor",7%, IF(C3="Keyboard",5%, IF(C3="Mouse",5%,0)))))) -> 0.08 | G3: 3200 | H3: Bella | I3: Retail | J3: =MONTH(A3) -> 1
A4: 45294 | B4: East | C4: Smartphone | D4: 12 | E4: 700 | F4: =IF(C4="Laptop",10%, IF(C4="Tablet",8%, IF(C4="Smartphone",12%, IF(C4="Monitor",7%, IF(C4="Keyboard",5%, IF(C4="Mouse",5%,0)))))) -> 0.12 | G4: 8400 | H4: Chris | I4: Online | J4: =MONTH(A4) -> 1 | K4: {=_xlfn._xlws.FILTER(Table1[],Table1[Product]="Mouse","Not found")} -> 45297 | L4: South | M4: Mouse | N4: 30 | O4: 25 | P4: 0.05 | Q4: 750 | R4: Bella | S4: Online | T4: 1
A5: 45295 | B5: West | C5: Monitor | D5: 10 | E5: 250 | F5: =IF(C5="Laptop",10%, IF(C5="Tablet",8%, IF(C5="Smartphone",12%, IF(C5="Monitor",7%, IF(C5="Keyboard",5%, IF(C5="Mouse",5%,0)))))) -> 0.07 | G5: 2500 | H5: Diana | I5: Wholesale | J5: =MONTH(A5) -> 1 | K5: 45303 | L5: West | M5: Mouse | N5: 35 | O5: 25 | P5: 0.05 | Q5: 875 | R5: Diana | S5: Online | T5: 1
A6: 45296 | B6: North | C6: Keyboard | D6: 20 | E6: 50 | F6: =IF(C6="Laptop",10%, IF(C6="Tablet",8%, IF(C6="Smartphone",12%, IF(C6="Monitor",7%, IF(C6="Keyboard",5%, IF(C6="Mouse",5%,0)))))) -> 0.05 | G6: 1000 | H6: Alex | I6: Retail | J6: =MONTH(A6) -> 1 | K6: 45309 | L6: South | M6: Mouse | N6: 40 | O6: 25 | P6: 0.05 | Q6: 1000 | R6: Bella | S6: Retail | T6: 1
A7: 45297 | B7: South | C7: Mouse | D7: 30 | E7: 25 | F7: =IF(C7="Laptop",10%, IF(C7="Tablet",8%, IF(C7="Smartphone",12%, IF(C7="Monitor",7%, IF(C7="Keyboard",5%, IF(C7="Mouse",5%,0)))))) -> 0.05 | G7: 750 | H7: Bella | I7: Online | J7: =MONTH(A7) -> 1 | K7: 45315 | L7: West | M7: Mouse | N7: 28 | O7: 25 | P7: 0.05 | Q7: 700 | R7: Diana | S7: Retail | T7: 1
A8: 45298 | B8: East | C8: Laptop | D8: 6 | E8: 900 | F8: =IF(C8="Laptop",10%, IF(C8="Tablet",8%, IF(C8="Smartphone",12%, IF(C8="Monitor",7%, IF(C8="Keyboard",5%, IF(C8="Mouse",5%,0)))))) -> 0.1 | G8: 5400 | H8: Chris | I8: Wholesale | J8: =MONTH(A8) -> 1 | K8: 45321 | L8: South | M8: Mouse | N8: 45 | O8: 25 | P8: 0.05 | Q8: 1125 | R8: Bella | S8: Retail | T8: 1
A9: 45299 | B9: West | C9: Tablet | D9: 9 | E9: 400 | F9: =IF(C9="Laptop",10%, IF(C9="Tablet",8%, IF(C9="Smartphone",12%, IF(C9="Monitor",7%, IF(C9="Keyboard",5%, IF(C9="Mouse",5%,0)))))) -> 0.08 | G9: 3600 | H9: Diana | I9: Retail | J9: =MONTH(A9) -> 1 | K9: 45327 | L9: West | M9: Mouse | N9: 33 | O9: 25 | P9: 0.05 | Q9: 825 | R9: Diana | S9: Wholesale | T9: 2
A10: 45300 | B10: North | C10: Smartphone | D10: 14 | E10: 700 | F10: =IF(C10="Laptop",10%, IF(C10="Tablet",8%, IF(C10="Smartphone",12%, IF(C10="Monitor",7%, IF(C10="Keyboard",5%, IF(C10="Mouse",5%,0)))))) -> 0.12 | G10: 9800 | H10: Alex | I10: Online | J10: =MONTH(A10) -> 1 | K10: 45333 | L10: South | M10: Mouse | N10: 38 | O10: 25 | P10: 0.05 | Q10: 950 | R10: Bella | S10: Retail | T10: 2
A11: 45301 | B11: South | C11: Monitor | D11: 11 | E11: 250 | F11: =IF(C11="Laptop",10%, IF(C11="Tablet",8%, IF(C11="Smartphone",12%, IF(C11="Monitor",7%, IF(C11="Keyboard",5%, IF(C11="Mouse",5%,0)))))) -> 0.07 | G11: 2750 | H11: Bella | I11: Wholesale | J11: =MONTH(A11) -> 1 | K11: 45339 | L11: West | M11: Mouse | N11: 42 | O11: 25 | P11: 0.05 | Q11: 1050 | R11: Diana | S11: Retail | T11: 2
A12: 45302 | B12: East | C12: Keyboard | D12: 22 | E12: 50 | F12: =IF(C12="Laptop",10%, IF(C12="Tablet",8%, IF(C12="Smartphone",12%, IF(C12="Monitor",7%, IF(C12="Keyboard",5%, IF(C12="Mouse",5%,0)))))) -> 0.05 | G12: 1100 | H12: Chris | I12: Retail | J12: =MONTH(A12) -> 1 | K12: 45345 | L12: South | M12: Mouse | N12: 36 | O12: 25 | P12: 0.05 | Q12: 900 | R12: Bella | S12: Wholesale | T12: 2
A13: 45303 | B13: West | C13: Mouse | D13: 35 | E13: 25 | F13: =IF(C13="Laptop",10%, IF(C13="Tablet",8%, IF(C13="Smartphone",12%, IF(C13="Monitor",7%, IF(C13="Keyboard",5%, IF(C13="Mouse",5%,0)))))) -> 0.05 | G13: 875 | H13: Diana | I13: Online | J13: =MONTH(A13) -> 1 | K13: 45351 | L13: West | M13: Mouse | N13: 48 | O13: 25 | P13: 0.05 | Q13: 1200 | R13: Diana | S13: Online | T13: 2
A14: 45304 | B14: North | C14: Laptop | D14: 4 | E14: 900 | F14: =IF(C14="Laptop",10%, IF(C14="Tablet",8%, IF(C14="Smartphone",12%, IF(C14="Monitor",7%, IF(C14="Keyboard",5%, IF(C14="Mouse",5%,0)))))) -> 0.1 | G14: 3600 | H14: Alex | I14: Retail | J14: =MONTH(A14) -> 1
A15: 45305 | B15: South | C15: Tablet | D15: 7 | E15: 400 | F15: =IF(C15="Laptop",10%, IF(C15="Tablet",8%, IF(C15="Smartphone",12%, IF(C15="Monitor",7%, IF(C15="Keyboard",5%, IF(C15="Mouse",5%,0)))))) -> 0.08 | G15: 2800 | H15: Bella | I15: Online | J15: =MONTH(A15) -> 1
A16: 45306 | B16: East | C16: Smartphone | D16: 10 | E16: 700 | F16: =IF(C16="Laptop",10%, IF(C16="Tablet",8%, IF(C16="Smartphone",12%, IF(C16="Monitor",7%, IF(C16="Keyboard",5%, IF(C16="Mouse",5%,0)))))) -> 0.12 | G16: 7000 | H16: Chris | I16: Wholesale | J16: =MONTH(A16) -> 1
A17: 45307 | B17: West | C17: Monitor | D17: 12 | E17: 250 | F17: =IF(C17="Laptop",10%, IF(C17="Tablet",8%, IF(C17="Smartphone",12%, IF(C17="Monitor",7%, IF(C17="Keyboard",5%, IF(C17="Mouse",5%,0)))))) -> 0.07 | G17: 3000 | H17: Diana | I17: Retail | J17: =MONTH(A17) -> 1
A18: 45308 | B18: North | C18: Keyboard | D18: 25 | E18: 50 | F18: =IF(C18="Laptop",10%, IF(C18="Tablet",8%, IF(C18="Smartphone",12%, IF(C18="Monitor",7%, IF(C18="Keyboard",5%, IF(C18="Mouse",5%,0)))))) -> 0.05 | G18: 1250 | H18: Alex | I18: Online | J18: =MONTH(A18) -> 1
A19: 45309 | B19: South | C19: Mouse | D19: 40 | E19: 25 | F19: =IF(C19="Laptop",10%, IF(C19="Tablet",8%, IF(C19="Smartphone",12%, IF(C19="Monitor",7%, IF(C19="Keyboard",5%, IF(C19="Mouse",5%,0)))))) -> 0.05 | G19: 1000 | H19: Bella | I19: Retail | J19: =MONTH(A19) -> 1
A20: 45310 | B20: East | C20: Laptop | D20: 8 | E20: 900 | F20: =IF(C20="Laptop",10%, IF(C20="Tablet",8%, IF(C20="Smartphone",12%, IF(C20="Monitor",7%, IF(C20="Keyboard",5%, IF(C20="Mouse",5%,0)))))) -> 0.1 | G20: 7200 | H20: Chris | I20: Online | J20: =MONTH(A20) -> 1
A21: 45311 | B21: West | C21: Tablet | D21: 6 | E21: 400 | F21: =IF(C21="Laptop",10%, IF(C21="Tablet",8%, IF(C21="Smartphone",12%, IF(C21="Monitor",7%, IF(C21="Keyboard",5%, IF(C21="Mouse",5%,0)))))) -> 0.08 | G21: 2400 | H21: Diana | I21: Wholesale | J21: =MONTH(A21) -> 1
A22: 45312 | B22: North | C22: Smartphone | D22: 15 | E22: 700 | F22: =IF(C22="Laptop",10%, IF(C22="Tablet",8%, IF(C22="Smartphone",12%, IF(C22="Monitor",7%, IF(C22="Keyboard",5%, IF(C22="Mouse",5%,0)))))) -> 0.12 | G22: 10500 | H22: Alex | I22: Retail | J22: =MONTH(A22) -> 1
A23: 45313 | B23: South | C23: Monitor | D23: 9 | E23: 250 | F23: =IF(C23="Laptop",10%, IF(C23="Tablet",8%, IF(C23="Smartphone",12%, IF(C23="Monitor",7%, IF(C23="Keyboard",5%, IF(C23="Mouse",5%,0)))))) -> 0.07 | G23: 2250 | H23: Bella | I23: Online | J23: =MONTH(A23) -> 1
A24: 45314 | B24: East | C24: Keyboard | D24: 18 | E24: 50 | F24: =IF(C24="Laptop",10%, IF(C24="Tablet",8%, IF(C24="Smartphone",12%, IF(C24="Monitor",7%, IF(C24="Keyboard",5%, IF(C24="Mouse",5%,0)))))) -> 0.05 | G24: 900 | H24: Chris | I24: Wholesale | J24: =MONTH(A24) -> 1
A25: 45315 | B25: West | C25: Mouse | D25: 28 | E25: 25 | F25: =IF(C25="Laptop",10%, IF(C25="Tablet",8%, IF(C25="Smartphone",12%, IF(C25="Monitor",7%, IF(C25="Keyboard",5%, IF(C25="Mouse",5%,0)))))) -> 0.05 | G25: 700 | H25: Diana | I25: Retail | J25: =MONTH(A25) -> 1
... A61: 45351 | B61: West | C61: Mouse | D61: 48 | E61: 25 | F61: =IF(C61="Laptop",10%, IF(C61="Tablet",8%, IF(C61="Smartphone",12%, IF(C61="Monitor",7%, IF(C61="Keyboard",5%, IF(C61="Mouse",5%,0)))))) -> 0.05 | G61: 1200 | H61: Diana | I61: Online | J61: =MONTH(A61) -> 2

Sheet Sales Analysis
A1: Sales_Person | B1: Total Revenue Generated by Sales Person | E1: Sales Channel | F1: Total Revenue Generated through Sales Channel | I1: Region | J1: Total Revenue Region Wise
A2: {=_xlfn.UNIQUE(Table1[Sales_Person])} -> Alex | B2: =SUMIF(Table1[Sales_Person],A2,Table1[Revenue]) -> 88200 | E2: {=_xlfn.UNIQUE(Table1[Sales_Channel])} -> Online | F2: =SUMIF(Table1[Sales_Channel],E2,Table1[Revenue]) -> 81675 | I2: {=_xlfn.UNIQUE(Table1[Region])} -> North | J2: =SUMIF(Table1[Region],I2,Table1[Revenue]) -> 88200
A3: Bella | B3: =SUMIF(Table1[Sales_Person],A3,Table1[Revenue]) -> 35275 | E3: Retail | F3: =SUMIF(Table1[Sales_Channel],E3,Table1[Revenue]) -> 88825 | I3: South | J3: =SUMIF(Table1[Region],I3,Table1[Revenue]) -> 35275
A4: Chris | B4: =SUMIF(Table1[Sales_Person],A4,Table1[Revenue]) -> 76150 | E4: Wholesale | F4: =SUMIF(Table1[Sales_Channel],E4,Table1[Revenue]) -> 65325 | I4: East | J4: =SUMIF(Table1[Region],I4,Table1[Revenue]) -> 76150
A5: Diana | B5: =SUMIF(Table1[Sales_Person],A5,Table1[Revenue]) -> 36200 | E5: Total | F5: =SUM(F2:F4) -> 235825 | I5: West | J5: =SUMIF(Table1[Region],I5,Table1[Revenue]) -> 36200
A6: Total | B6: =SUM(B2:B5) -> 235825 | I6: Total | J6: =SUM(J2:K5) -> 235825
A8: Product | B8: Qty Sold of Different Products | E8: Region | F8: Qty Sold in Different Regions
A9: {=_xlfn.UNIQUE(Table1[Product])} -> Laptop | B9: =SUMIF(Table1[Product],A9,Table1[Units_Sold]) -> 67 | E9: {=_xlfn.UNIQUE(Table1[Region])} -> North | F9: =SUMIF(Table1[Region],E9,Table1[Units_Sold]) -> 233
A10: Tablet | B10: =SUMIF(Table1[Product],A10,Table1[Units_Sold]) -> 84 | E10: South | F10: =SUMIF(Table1[Region],E10,Table1[Units_Sold]) -> 286
A11: Smartphone | B11: =SUMIF(Table1[Product],A11,Table1[Units_Sold]) -> 132 | E11: East | F11: =SUMIF(Table1[Region],E11,Table1[Units_Sold]) -> 199
A12: Monitor | B12: =SUMIF(Table1[Product],A12,Table1[Units_Sold]) -> 114 | E12: West | F12: =SUMIF(Table1[Region],E12,Table1[Units_Sold]) -> 287
A13: Keyboard | B13: =SUMIF(Table1[Product],A13,Table1[Units_Sold]) -> 233 | E13: Total | F13: =SUM(F9:F12) -> 1005
A14: Mouse | B14: =SUMIF(Table1[Product],A14,Table1[Units_Sold]) -> 375
A15: Total | B15: =SUM(B9:B14) -> 1005

Sheet WHAT-IF Analysis
A1: SCENARIO MANAGER
A4: Input (Discount ) | B4: Output ( Total Revenue / Sales ) | C4: Sales / Revenue as per Comman Discount
A5: 0.12 | B5: =SUM(C5:C64) -> 207526 | C5: ='Project Database'!G2*(1-$A$5) -> 3960
C6: ='Project Database'!G3*(1-$A$5) -> 2816
C7: ='Project Database'!G4*(1-$A$5) -> 7392
C8: ='Project Database'!G5*(1-$A$5) -> 2200
C9: ='Project Database'!G6*(1-$A$5) -> 880
C10: ='Project Database'!G7*(1-$A$5) -> 660
C11: ='Project Database'!G8*(1-$A$5) -> 4752
C12: ='Project Database'!G9*(1-$A$5) -> 3168
C13: ='Project Database'!G10*(1-$A$5) -> 8624
C14: ='Project Database'!G11*(1-$A$5) -> 2420
C15: ='Project Database'!G12*(1-$A$5) -> 968
C16: ='Project Database'!G13*(1-$A$5) -> 770
C17: ='Project Database'!G14*(1-$A$5) -> 3168
... C64: ='Project Database'!G61*(1-$A$5) -> 1056
